{"validationEntity":{"dataResult":{"createdDate":"2024-03-20T15:23:21Z"},"analysedDataType":"auto"},"modelEntity":{"title":"","createdDate":"2024-03-20T15:23:21Z","version":"1.0","modifiedDate":"2024-03-20T15:23:21Z","experimentID":"E171F51F-E185-4EEB-A51F-7C32C06412E7","id":"440FA4F2-2844-4551-8F10-9BA9FBAB8A68","preferredFilename":"","modelURL":"Models\/BetterRest%201%20Linear%20Regression.mlmodel"},"modifiedDate":"2024-03-20T15:23:44Z","version":"1.0","evaluationContainerEntity":{"id":"7c8adb54-1d7a-4ad7-a08d-6bcc76a408ef","trainingEvaluationEntity":{"dataSourceID":"B2E1C8E7-E501-4C8B-B113-6C2AC7011952","analysedDataType":"none","id":"95a292b9-e5b4-4f52-8884-06b184bedd63","dataResult":{"targetRange":[19216,45224],"itemsCount":10000,"createdDate":"2024-03-20T15:23:21Z","dataSourceID":"B2E1C8E7-E501-4C8B-B113-6C2AC7011952","dataAnalysis":{"summary":{"canUseValidation":1,"sampleCount":10000},"regressorAnalysis":{"targetRange":[19216,45224]},"classifierAnalysis":{},"issues":[{"description":"Data has 10000 rows","severity":"info"}]},"dataURL":"file:\/\/\/Users\/marcusbenoit\/Library\/Mobile%20Documents\/com~apple~CloudDocs\/Coding\/100SwiftUI\/Project4%20-%20BetterRest\/BetterRest.csv"},"evaluationResult":{"generalRegressor":{"maximumError":703.3447823655588,"rootMeanSquaredError":176.97923597171882}},"createdDate":"2024-03-20T15:23:21Z"},"previewType":"tabularRegressor","validationEvaluationEntity":{"dataResult":{"createdDate":"2024-03-20T15:23:21Z"},"createdDate":"2024-03-20T15:23:21Z","evaluationResult":{"generalRegressor":{"rootMeanSquaredError":178.33863495350846,"maximumError":691.3366487775202}},"id":"4ea78aad-7210-4c49-a10d-a77344f62baa","analysedDataType":"auto"},"evaluationEntities":[{"dataResult":{},"createdDate":"2024-03-20T15:23:44Z","analysedDataType":"none","id":"c638bc3a-932d-43b5-bcf0-eca3b11f4452"}],"modifiedDate":"2024-03-20T15:23:44Z","testingEvaluationEntity":{"createdDate":"2024-03-20T15:23:21Z","id":"039f30fa-929b-4d85-bf34-82c8d650aff7","analysedDataType":"none","dataResult":{"createdDate":"2024-03-20T15:23:21Z"}},"createdDate":"2024-03-20T15:23:44Z"},"state":"trained","title":"BetterRest 1 Decision Tree copy","contentDataResult":{"createdDate":"2024-03-20T14:03:34Z"},"preferredFilename":"BetterRest 1 Linear Regression","evaluationEntity":{"analysedDataType":"none","id":"ecb6b4c9-32ad-4434-aea3-5fc149408f6e","dataResult":{}},"activityEntities":["trainingFinished",[{"subtitle":"10 iterations","createdDate":"2024-03-20T15:23:42Z","title":"Training Completed","id":"270D3C45-5923-4C0C-A824-EBF445C114B5","event":"trainingFinished"}],"trainingDataAdded",[{"subtitle":"BetterRest.csv","createdDate":"2024-03-20T15:23:21Z","event":"trainingDataAdded","title":"Training Data Added","id":"79A8A722-3156-44AC-B31D-1B629BB7B77C"}],"trainingStarted",[{"id":"09747F34-A6F2-4D28-A2A9-792D738C37BB","event":"trainingStarted","title":"Training Started","subtitle":"10 iterations","createdDate":"2024-03-20T15:23:41Z"}],"experimentCreated",[{"title":"Model Source Created","event":"experimentCreated","id":"37C1B928-3A0C-4E94-B231-1122B66E2424","subtitle":"BetterRest 1 Linear Regression","createdDate":"2024-03-20T15:23:21Z"}]],"evaluationState":"uninitialized","settingEntity":{"transferLearningEmbeddingType":"dynamic","targetColumn":"actualSleep","suggestedColumns":["wake","estimatedSleep","coffee","actualSleep"],"styleTransferAlgorithmType":"image","generalRegressorType":{"linearRegression":{"l1Penalty":0,"stepSize":1,"l2Penalty":0.01,"convergenceThreshold":0.01,"featureScaling":true}},"taskType":"generalRegresor","suggestedColumnTypes":["Int","Double","Int","Int"],"featureNames":["wake","estimatedSleep","coffee"],"handPoseClassifierAugmentations":[],"harVideoAugmentations":0,"iterationCount":10,"suggestedColumnValues":["31.500, 32.400, 26.100, 40.500, 19.800, 27.000, 20.700, 21.600, 41.400, 34.200, 21.600, 78.300, 32.400, 28.800, 18.900, 18.000, 28.800, 18.000, 7.200, 35.100, 24.300, 35.100, 34.200, 27.900, 30.600, 69.300, 35.100, 34.200, 34.200, 23.400","9,00, 5,00, 6,50, 8,75, 6,00, 7,50, 9,25, 6,00, 9,25, 6,75, 5,25, 9,25, 10,00, 8,75, 8,25, 6,25, 10,00, 6,25, 10,00, 9,50, 5,00, 7,50, 6,25, 8,00, 8,00, 6,50, 8,00, 10,00, 8,25, 8,00","6, 2, 10, 4, 3, 1, 1, 3, 5, 8, 3, 8, 2, 3, 1, 2, 3, 2, 1, 4, 2, 1, 1, 4, 3, 7, 4, 4, 1, 3","38.230, 20.180, 31.989, 35.258, 24.487, 28.300, 34.548, 24.557, 37.836, 31.340, 21.874, 40.405, 38.076, 34.265, 30.936, 24.665, 39.007, 24.578, 37.267, 37.878, 20.220, 28.400, 23.882, 32.427, 31.699, 29.670, 32.789, 39.792, 30.935, 31.701"],"seedType":"default","algorithmType":"maxEnt","handActionClassifierAugmentations":[],"augmentations":[]},"createdDate":"2024-03-20T15:23:21Z","trainingEntity":{"snapshottableCheckpoints":{},"featureExtractionCheckpointMayBeAvailable":false,"validationResults":{"generalRegressor":{"rootMeanSquaredError":178.33863495350846,"maximumError":691.3366487775202}},"trainingResults":{"generalRegressor":{"rootMeanSquaredError":176.97923597171882,"maximumError":703.3447823655588}},"finishTime":"2024-03-20T15:23:42Z","analysedDataType":"datasource","dataSourceID":"B2E1C8E7-E501-4C8B-B113-6C2AC7011952","progress":[],"dataResult":{"dataAnalysis":{"summary":{"canUseValidation":1,"sampleCount":10000},"regressorAnalysis":{"targetRange":[19216,45224]},"issues":[{"description":"Data has 10000 rows","severity":"info"}],"classifierAnalysis":{}},"dataURL":"file:\/\/\/Users\/marcusbenoit\/Library\/Mobile%20Documents\/com~apple~CloudDocs\/Coding\/100SwiftUI\/Project4%20-%20BetterRest\/BetterRest.csv","columnValues":["31.500, 32.400, 26.100, 40.500, 19.800, 27.000, 20.700, 21.600, 41.400, 34.200, 21.600, 78.300, 32.400, 28.800, 18.900, 18.000, 28.800, 18.000, 7.200, 35.100, 24.300, 35.100, 34.200, 27.900, 30.600, 69.300, 35.100, 34.200, 34.200, 23.400","9,00, 5,00, 6,50, 8,75, 6,00, 7,50, 9,25, 6,00, 9,25, 6,75, 5,25, 9,25, 10,00, 8,75, 8,25, 6,25, 10,00, 6,25, 10,00, 9,50, 5,00, 7,50, 6,25, 8,00, 8,00, 6,50, 8,00, 10,00, 8,25, 8,00","6, 2, 10, 4, 3, 1, 1, 3, 5, 8, 3, 8, 2, 3, 1, 2, 3, 2, 1, 4, 2, 1, 1, 4, 3, 7, 4, 4, 1, 3","38.230, 20.180, 31.989, 35.258, 24.487, 28.300, 34.548, 24.557, 37.836, 31.340, 21.874, 40.405, 38.076, 34.265, 30.936, 24.665, 39.007, 24.578, 37.267, 37.878, 20.220, 28.400, 23.882, 32.427, 31.699, 29.670, 32.789, 39.792, 30.935, 31.701"],"itemsCount":10000,"targetRange":[19216,45224],"dataSourceID":"B2E1C8E7-E501-4C8B-B113-6C2AC7011952","createdDate":"2024-03-20T15:23:21Z","columnTypes":["Int","Double","Int","Int"],"columns":["wake","estimatedSleep","coffee","actualSleep"]},"checkpointMetrics":{},"startTime":"2024-03-20T15:23:41Z","validationAccuracy":178.33863495350846,"trainingAccuracy":176.97923597171882},"snapshotRole":{"withoutSnapshots":0},"id":"AECE82F1-D56F-4B70-9945-5AE16E783C65"}